kttool/VERSION
kttool/__init__.py
kttool/base.py
kttool/context.py
kttool/logger.py
kttool/parser.py
kttool/utils.py
kttool/version.py
kttool/actions/__init__.py
kttool/actions/config.py
kttool/actions/gen.py
kttool/actions/open.py
kttool/actions/submit.py
kttool/actions/surprise.py
kttool/actions/test.py
kttool/actions/update.py
kttool/actions/version.py
kttool/default_templates/template.c
kttool/default_templates/template.cc
kttool/default_templates/template.cpp
kttool/default_templates/template.go
kttool/default_templates/template.java
kttool/default_templates/template.js
kttool/default_templates/template.py
kttool/default_templates/template.rs
kttool-1.3.5.data/data/kttool/LICENSE
kttool-1.3.5.data/data/kttool/VERSION
kttool-1.3.5.data/data/kttool/requirements.txt
kttool-1.3.5.data/data/kttool/template.c
kttool-1.3.5.data/data/kttool/template.cc
kttool-1.3.5.data/data/kttool/template.cpp
kttool-1.3.5.data/data/kttool/template.go
kttool-1.3.5.data/data/kttool/template.java
kttool-1.3.5.data/data/kttool/template.js
kttool-1.3.5.data/data/kttool/template.py
kttool-1.3.5.data/data/kttool/template.rs
kttool-1.3.5.data/scripts/kt
src/__init__.py
src/base.py
src/context.py
src/logger.py
src/parser.py
src/utils.py
src/version.py
src/actions/__init__.py
src/actions/config.py
src/actions/gen.py
src/actions/open.py
src/actions/submit.py
src/actions/test.py
src/actions/update.py
src/actions/version.py
kttool-1.3.5.dist-info/LICENSE
kttool-1.3.5.dist-info/METADATA
kttool-1.3.5.dist-info/WHEEL
kttool-1.3.5.dist-info/top_level.txt
kttool-1.3.5.dist-info/RECORD
