Metadata-Version: 2.1
Name: kttool
Version: 1.3.5
Summary: Kattis command line tool
Home-page: https://github.com/heiseish/kt
Author: Dao Truong Giang
Author-email: dtrnggiang@gmail.com
License: MIT
Platform: UNKNOWN
Classifier: Operating System :: MacOS :: MacOS X
Classifier: Operating System :: Microsoft :: Windows
Classifier: Operating System :: POSIX
Classifier: License :: OSI Approved :: MIT License
Classifier: Programming Language :: Python :: 3
Classifier: Programming Language :: Python :: 3.7
License-File: LICENSE
Requires-Dist: requests (==2.28.1)
Requires-Dist: bs4 (==0.0.1)
Requires-Dist: emoji (==0.6.0)
Requires-Dist: reprint (==0.5.2)
Requires-Dist: psutil (==5.9.4)
Requires-Dist: pytest (==7.2.0)
Requires-Dist: typing-extensions (==4.1.1)
